Metadata-Version: 1.0
Name: binogaus
Version: 0.1
Summary: Binomial and Gaussian distributions
Home-page: UNKNOWN
Author: Niyaz B. Hashem
Author-email: UNKNOWN
License: UNKNOWN
Platform: UNKNOWN
